{
  "12 years a slave": {},
  "1991\n\n|  who gets to fly\n\n|  come dance with me\n\n|  we want a beautiful life\n\n|  what you will have seen\n\n|  existence and plurality\n\n|  why some people be mad at me sometimes\n\n|  xxxxxxx\n\n|  eautopsie": {},
  "19th century georgian chronicle": {
    "rating": 3.58,
    "slug": "19th-century-georgian-chronicle",
    "url": "https://letterboxd.com/film/19th-century-georgian-chronicle/"
  },
  "2001: a space odyssey": {
    "rating": 4.25,
    "slug": "2001-a-space-odyssey",
    "url": "https://letterboxd.com/film/2001-a-space-odyssey/"
  },
  "8 1/2": {},
  "8 times\n\n|  [sniff]\n\n|  rap world day\n\n|  this is home\n\n|  lespri\n\n|  pi\u00f1ata prayers": {},
  "<---> (back and forth)": {},
  "a bay of blood": {},
  "a body to live in": {
    "rating": 3.51,
    "slug": "a-body-to-live-in",
    "url": "https://letterboxd.com/film/a-body-to-live-in/"
  },
  "a clockwork orange": {},
  "a life illuminated": {},
  "a litany for survival: the life and work of audre lorde": {},
  "a mighty wind": {
    "rating": 3.67,
    "slug": "a-mighty-wind",
    "url": "https://letterboxd.com/film/a-mighty-wind/"
  },
  "a missing can of film\n\n|  ultramarine": {},
  "a new love in tokyo": {
    "rating": 3.9,
    "slug": "a-new-love-in-tokyo",
    "url": "https://letterboxd.com/film/a-new-love-in-tokyo/"
  },
  "a nightmare on elm street 3: dream warriors": {},
  "a place in the sun": {
    "rating": 3.94,
    "slug": "a-place-in-the-sun",
    "url": "https://letterboxd.com/film/a-place-in-the-sun/"
  },
  "a poet": {
    "rating": null,
    "slug": "milano-cortina-2026-olympic-closing-ceremony",
    "url": "https://letterboxd.com/film/milano-cortina-2026-olympic-closing-ceremony/"
  },
  "a real young girl": {
    "rating": 3.22,
    "slug": "a-real-young-girl",
    "url": "https://letterboxd.com/film/a-real-young-girl/"
  },
  "a serious man": {
    "rating": 3.86,
    "slug": "a-serious-man",
    "url": "https://letterboxd.com/film/a-serious-man/"
  },
  "a sixth of the world": {},
  "a stolen meeting": {},
  "a subway story\n\n|  off the rails": {},
  "a summer at grandpa's": {
    "rating": 3.91,
    "slug": "a-summer-at-grandpas",
    "url": "https://letterboxd.com/film/a-summer-at-grandpas/"
  },
  "abdo and saneya": {
    "rating": null,
    "slug": "abdo-and-saneya",
    "url": "https://letterboxd.com/film/abdo-and-saneya/"
  },
  "adjunct\n\n|  dirt\n\n|  play dead!": {},
  "affection affection": {
    "rating": null,
    "slug": "affection-affection",
    "url": "https://letterboxd.com/film/affection-affection/"
  },
  "after hours": {
    "rating": 4.13,
    "slug": "after-hours",
    "url": "https://letterboxd.com/film/after-hours/"
  },
  "after the reconciliation": {
    "rating": 3.61,
    "slug": "after-the-reconciliation",
    "url": "https://letterboxd.com/film/after-the-reconciliation/"
  },
  "agn\u00e8s varda: from here to there (episodes 1-3)": {},
  "agn\u00e8s varda: from here to there (episodes 4-5)": {},
  "agon": {},
  "alam": {
    "rating": 3.73,
    "slug": "alam",
    "url": "https://letterboxd.com/film/alam/"
  },
  "ali: fear eats the soul": {
    "rating": 4.18,
    "slug": "ali-fear-eats-the-soul",
    "url": "https://letterboxd.com/film/ali-fear-eats-the-soul/"
  },
  "alice": {},
  "all about eve": {
    "rating": 4.36,
    "slug": "all-about-eve",
    "url": "https://letterboxd.com/film/all-about-eve/"
  },
  "all about my mother": {
    "rating": 4.19,
    "slug": "all-about-my-mother",
    "url": "https://letterboxd.com/film/all-about-my-mother/"
  },
  "all that's left of you": {
    "rating": 4.18,
    "slug": "all-thats-left-of-you",
    "url": "https://letterboxd.com/film/all-thats-left-of-you/"
  },
  "allegro non troppo": {
    "rating": 3.82,
    "slug": "allegro-non-troppo",
    "url": "https://letterboxd.com/film/allegro-non-troppo/"
  },
  "almanac of fall": {
    "rating": 3.7,
    "slug": "autumn-almanac",
    "url": "https://letterboxd.com/film/autumn-almanac/"
  },
  "alpha": {
    "rating": null,
    "slug": "alpha-2026",
    "url": "https://letterboxd.com/film/alpha-2026/"
  },
  "altar\n\n|  the conquest of faro": {},
  "alyonka": {},
  "amadeus": {
    "rating": 4.35,
    "slug": "amadeus",
    "url": "https://letterboxd.com/film/amadeus/"
  },
  "amarcord": {
    "rating": 4.13,
    "slug": "amarcord",
    "url": "https://letterboxd.com/film/amarcord/"
  },
  "american dendrite": {
    "rating": null,
    "slug": "american-dendrite",
    "url": "https://letterboxd.com/film/american-dendrite/"
  },
  "american movie": {},
  "am\u00edlcar": {
    "rating": null,
    "slug": "amilcar",
    "url": "https://letterboxd.com/film/amilcar/"
  },
  "an american werewolf in london": {
    "rating": 3.83,
    "slug": "an-american-werewolf-in-london",
    "url": "https://letterboxd.com/film/an-american-werewolf-in-london/"
  },
  "anatomy of a fall": {},
  "and the roots of rhythm remain": {},
  "andr\u00e9 is an idiot": {
    "rating": 3.9,
    "slug": "andre-is-an-idiot",
    "url": "https://letterboxd.com/film/andre-is-an-idiot/"
  },
  "angel's egg": {
    "rating": 4.1,
    "slug": "angels-egg",
    "url": "https://letterboxd.com/film/angels-egg/"
  },
  "animated oscar-nominated shorts 2026": {},
  "anna": {
    "rating": 3.49,
    "slug": "anna",
    "url": "https://letterboxd.com/film/anna/"
  },
  "arnaud desplechin presents shoah": {},
  "aro berria": {},
  "art cinema for tots: journeys": {},
  "at work": {
    "rating": 3.14,
    "slug": "at-work-2025",
    "url": "https://letterboxd.com/film/at-work-2025/"
  },
  "atanarjuat: the fast runner": {
    "rating": 3.72,
    "slug": "atanarjuat-the-fast-runner",
    "url": "https://letterboxd.com/film/atanarjuat-the-fast-runner/"
  },
  "atropia": {
    "rating": 3.25,
    "slug": "atropia",
    "url": "https://letterboxd.com/film/atropia/"
  },
  "battle royale": {
    "rating": 3.86,
    "slug": "battle-royale",
    "url": "https://letterboxd.com/film/battle-royale/"
  },
  "beau travail": {
    "rating": 4.12,
    "slug": "beau-travail",
    "url": "https://letterboxd.com/film/beau-travail/"
  },
  "beetlejuice": {
    "rating": 3.73,
    "slug": "beetlejuice",
    "url": "https://letterboxd.com/film/beetlejuice/"
  },
  "beijing bicycle": {
    "rating": 3.62,
    "slug": "beijing-bicycle",
    "url": "https://letterboxd.com/film/beijing-bicycle/"
  },
  "berlin, symphony of a city\n\n|  sausalito": {},
  "best in show": {
    "rating": 3.87,
    "slug": "best-in-show",
    "url": "https://letterboxd.com/film/best-in-show/"
  },
  "big hero 6": {
    "rating": 3.84,
    "slug": "big-hero-6",
    "url": "https://letterboxd.com/film/big-hero-6/"
  },
  "billy preston: that's the way god planned it": {
    "rating": null,
    "slug": "billy-preston-thats-the-way-god-planned-it",
    "url": "https://letterboxd.com/film/billy-preston-thats-the-way-god-planned-it/"
  },
  "birders: the central park effect": {
    "rating": 3.54,
    "slug": "birders-the-central-park-effect",
    "url": "https://letterboxd.com/film/birders-the-central-park-effect/"
  },
  "birth": {
    "rating": 3.71,
    "slug": "birth-2004",
    "url": "https://letterboxd.com/film/birth-2004/"
  },
  "bitter rice (riso amaro)": {},
  "black girl": {},
  "black girl\n\n|  borom sarret": {},
  "black is... black ain't": {},
  "black orpheus": {
    "rating": 3.82,
    "slug": "black-orpheus",
    "url": "https://letterboxd.com/film/black-orpheus/"
  },
  "bleat!\n\n|  taxi moto\n\n|  buckskin\n\n|  only angels\n\n|  sabura": {},
  "blind woman\u2019s curse": {},
  "blknws: terms and conditions": {
    "rating": 3.8,
    "slug": "blknws-terms-conditions",
    "url": "https://letterboxd.com/film/blknws-terms-conditions/"
  },
  "blood barn": {},
  "blue fire": {
    "rating": null,
    "slug": "blue-fire",
    "url": "https://letterboxd.com/film/blue-fire/"
  },
  "blue heron": {},
  "blue velvet": {},
  "book of shadows: blair witch 2": {},
  "bountiful summer": {},
  "brand new landscape": {},
  "brand x": {
    "rating": null,
    "slug": "brand-x",
    "url": "https://letterboxd.com/film/brand-x/"
  },
  "bride of chucky": {},
  "bright leaves": {
    "rating": 3.72,
    "slug": "bright-leaves",
    "url": "https://letterboxd.com/film/bright-leaves/"
  },
  "bringing up baby": {},
  "broadway express\n\n|  new yorkers": {},
  "bullitt": {
    "rating": 3.73,
    "slug": "bullitt",
    "url": "https://letterboxd.com/film/bullitt/"
  },
  "bunnylovr": {},
  "burn after reading": {},
  "bus stop": {
    "rating": 2.79,
    "slug": "bus-stop",
    "url": "https://letterboxd.com/film/bus-stop/"
  },
  "by the bluest of seas": {},
  "by the time it gets dark": {
    "rating": 3.6,
    "slug": "by-the-time-it-gets-dark",
    "url": "https://letterboxd.com/film/by-the-time-it-gets-dark/"
  },
  "cach\u00e9": {
    "rating": 4.06,
    "slug": "cache",
    "url": "https://letterboxd.com/film/cache/"
  },
  "calle m\u00e1laga": {
    "rating": 3.73,
    "slug": "calle-malaga",
    "url": "https://letterboxd.com/film/calle-malaga/"
  },
  "cameraperson": {
    "rating": 4.14,
    "slug": "cameraperson",
    "url": "https://letterboxd.com/film/cameraperson/"
  },
  "camille claudel 1915": {
    "rating": 3.47,
    "slug": "camille-claudel-1915",
    "url": "https://letterboxd.com/film/camille-claudel-1915/"
  },
  "can she bake a cherry pie?": {
    "rating": 3.28,
    "slug": "can-she-bake-a-cherry-pie",
    "url": "https://letterboxd.com/film/can-she-bake-a-cherry-pie/"
  },
  "capitu": {
    "rating": 4.06,
    "slug": "capitu-2008",
    "url": "https://letterboxd.com/film/capitu-2008/"
  },
  "cara a cara": {
    "rating": 2.87,
    "slug": "larissa-the-other-side-of-anitta",
    "url": "https://letterboxd.com/film/larissa-the-other-side-of-anitta/"
  },
  "carrie": {
    "rating": 3.84,
    "slug": "carrie-1976",
    "url": "https://letterboxd.com/film/carrie-1976/"
  },
  "casa musgal\n\n|  l\u00f3matj\u00f6rn\n\n|  \u2600\u2605\u2708\u2190\u2192\n\n|  minevissam (i am writing)\n\n|  goodbye for now\n\n|  bxl 4ever": {},
  "case 137": {
    "rating": 3.5,
    "slug": "case-137-2025",
    "url": "https://letterboxd.com/film/case-137-2025/"
  },
  "cats": {},
  "caught in the acts": {},
  "cecil b. demented": {},
  "ceija stojka": {
    "rating": null,
    "slug": "ceija-stojka",
    "url": "https://letterboxd.com/film/ceija-stojka/"
  },
  "central park": {},
  "certified copy": {},
  "change my mind": {},
  "china 9, liberty 37": {},
  "chinatown": {},
  "chinese portrait": {
    "rating": 3.54,
    "slug": "chinese-portrait",
    "url": "https://letterboxd.com/film/chinese-portrait/"
  },
  "chronicle of the years of fire": {},
  "chronovisor": {},
  "cin\u00e9vardaphoto": {
    "rating": 3.59,
    "slug": "cinevardaphoto",
    "url": "https://letterboxd.com/film/cinevardaphoto/"
  },
  "citizen science: a symphony of human power - episode 1: citibikes\n\n|  the map\n\n|  changing lanes": {},
  "close encounters of the third kind": {
    "rating": 3.82,
    "slug": "close-encounters-of-the-third-kind",
    "url": "https://letterboxd.com/film/close-encounters-of-the-third-kind/"
  },
  "clouds of sils maria": {
    "rating": 3.68,
    "slug": "clouds-of-sils-maria",
    "url": "https://letterboxd.com/film/clouds-of-sils-maria/"
  },
  "clue": {},
  "cl\u00e9o from 5 to 7": {
    "rating": 4.18,
    "slug": "cleo-from-5-to-7",
    "url": "https://letterboxd.com/film/cleo-from-5-to-7/"
  },
  "code unknown": {
    "rating": 3.8,
    "slug": "code-unknown",
    "url": "https://letterboxd.com/film/code-unknown/"
  },
  "cold metal": {},
  "colors of time": {},
  "come see me in the good light": {
    "rating": 3.97,
    "slug": "come-see-me-in-the-good-light",
    "url": "https://letterboxd.com/film/come-see-me-in-the-good-light/"
  },
  "coming to america": {},
  "comrades: almost a love story": {
    "rating": 4.2,
    "slug": "comrades-almost-a-love-story",
    "url": "https://letterboxd.com/film/comrades-almost-a-love-story/"
  },
  "contempt": {
    "rating": 3.81,
    "slug": "contempt",
    "url": "https://letterboxd.com/film/contempt/"
  },
  "cool hand luke": {
    "rating": 4.16,
    "slug": "cool-hand-luke",
    "url": "https://letterboxd.com/film/cool-hand-luke/"
  },
  "cowboy bebop: the movie": {
    "rating": 4.12,
    "slug": "cowboy-bebop-the-movie",
    "url": "https://letterboxd.com/film/cowboy-bebop-the-movie/"
  },
  "crash": {
    "rating": 3.65,
    "slug": "crash",
    "url": "https://letterboxd.com/film/crash/"
  },
  "creed": {
    "rating": 3.81,
    "slug": "creed",
    "url": "https://letterboxd.com/film/creed/"
  },
  "crocodile dose": {},
  "crocodile dundee ii": {},
  "cruising": {
    "rating": 3.59,
    "slug": "cruising",
    "url": "https://letterboxd.com/film/cruising/"
  },
  "cr\u00eda cuervos": {
    "rating": 4.22,
    "slug": "cria",
    "url": "https://letterboxd.com/film/cria/"
  },
  "cure": {
    "rating": 4.27,
    "slug": "cure",
    "url": "https://letterboxd.com/film/cure/"
  },
  "cutting through rocks": {
    "rating": 3.8,
    "slug": "cutting-through-rocks",
    "url": "https://letterboxd.com/film/cutting-through-rocks/"
  },
  "cyclopean 3d: life with a beautiful woman\n\n|  flo rounds a corner": {},
  "daguerr\u00e9otypes": {},
  "dakan (destiny)": {
    "rating": 3.6,
    "slug": "destiny-1997",
    "url": "https://letterboxd.com/film/destiny-1997/"
  },
  "damnation": {
    "rating": 4.1,
    "slug": "damnation",
    "url": "https://letterboxd.com/film/damnation/"
  },
  "dance freak": {
    "rating": 3.69,
    "slug": "dance-freak",
    "url": "https://letterboxd.com/film/dance-freak/"
  },
  "dangerous seductress": {},
  "darjeeling limited": {
    "rating": 3.85,
    "slug": "the-darjeeling-limited",
    "url": "https://letterboxd.com/film/the-darjeeling-limited/"
  },
  "dark light\n\n|  star born brutal\n\n|  melencolia 2: destitution signs\n\n|  \u5047\u5982\u7942\u5011\u662f\u771f\u7684 (if they really exist)\n\n|  the full bloom\n\n|  sojourn": {},
  "daughter of nectar": {
    "rating": null,
    "slug": "daughter-of-nectar",
    "url": "https://letterboxd.com/film/daughter-of-nectar/"
  },
  "daybreak express\n\n|  style wars": {},
  "days and nights in the forest": {
    "rating": 3.95,
    "slug": "days-and-nights-in-the-forest",
    "url": "https://letterboxd.com/film/days-and-nights-in-the-forest/"
  },
  "de humani corporis fabrica": {
    "rating": 3.84,
    "slug": "de-humani-corporis-fabrica",
    "url": "https://letterboxd.com/film/de-humani-corporis-fabrica/"
  },
  "dead lover": {
    "rating": 2.88,
    "slug": "maigret-and-the-dead-lover",
    "url": "https://letterboxd.com/film/maigret-and-the-dead-lover/"
  },
  "dead man": {
    "rating": 3.92,
    "slug": "dead-man",
    "url": "https://letterboxd.com/film/dead-man/"
  },
  "dead pigs": {
    "rating": 3.57,
    "slug": "dead-pigs",
    "url": "https://letterboxd.com/film/dead-pigs/"
  },
  "defectors": {
    "rating": null,
    "slug": "defectors",
    "url": "https://letterboxd.com/film/defectors/"
  },
  "dekalog 1: i am the lord thy god\n\n|  dekalog 2: thou shalt not take the name of thy lord god in vain\n\n|  dekalog 3: honor the sabbath day\n\n|  dekalog 4: honor thy father and thy mother": {},
  "dekalog 5: thou shalt not kill\n\n|  dekalog 6: thou shalt not commit adultery\n\n|  dekalog 7: thou shalt not steal": {},
  "dekalog 8: thou shalt not bear false witness\n\n|  dekalog 9: thou shalt not covet thy neighbor's wife\n\n|  dekalog 10: thou shalt not covet thy neighbor's goods": {},
  "demonic scandal": {},
  "demonlover": {
    "rating": 3.55,
    "slug": "demonlover",
    "url": "https://letterboxd.com/film/demonlover/"
  },
  "desert hearts": {
    "rating": 3.81,
    "slug": "desert-hearts",
    "url": "https://letterboxd.com/film/desert-hearts/"
  },
  "deux fois\n\n|  chronicles of a lying spirit (by kelly gabron)": {},
  "dhrupad": {},
  "diary of a country priest": {
    "rating": 4.1,
    "slug": "diary-of-a-country-priest",
    "url": "https://letterboxd.com/film/diary-of-a-country-priest/"
  },
  "die hard": {
    "rating": 4.05,
    "slug": "die-hard",
    "url": "https://letterboxd.com/film/die-hard/"
  },
  "difficulty breathing\n\n|  the rope maiden": {},
  "digital man": {
    "rating": 2.91,
    "slug": "digital-man",
    "url": "https://letterboxd.com/film/digital-man/"
  },
  "dirty difficult dangerous": {
    "rating": 3.32,
    "slug": "dirty-difficult-dangerous",
    "url": "https://letterboxd.com/film/dirty-difficult-dangerous/"
  },
  "disclosure": {},
  "distant": {
    "rating": 3.95,
    "slug": "distant",
    "url": "https://letterboxd.com/film/distant/"
  },
  "dj ahmet": {},
  "do the right thing": {
    "rating": 4.4,
    "slug": "do-the-right-thing",
    "url": "https://letterboxd.com/film/do-the-right-thing/"
  },
  "do you love me": {},
  "doc program a: oscar- nominated shorts 2026": {},
  "doc program b: oscar-nominated shorts 2026": {},
  "documenteur": {
    "rating": 3.79,
    "slug": "documenteur",
    "url": "https://letterboxd.com/film/documenteur/"
  },
  "dolly": {
    "rating": null,
    "slug": "my-dear-dolly-2026",
    "url": "https://letterboxd.com/film/my-dear-dolly-2026/"
  },
  "don't bother to knock": {},
  "don't bother to knock\n\n|  marilyn times five": {},
  "donkey days": {},
  "donkey skin": {
    "rating": 4.0,
    "slug": "donkey-skin",
    "url": "https://letterboxd.com/film/donkey-skin/"
  },
  "donnie brasco": {},
  "donnie darko": {},
  "dope": {
    "rating": 3.5,
    "slug": "dope-2015",
    "url": "https://letterboxd.com/film/dope-2015/"
  },
  "downtown 81": {},
  "dr. jack": {},
  "drag me to hell": {
    "rating": 3.18,
    "slug": "drag-me-to-hell",
    "url": "https://letterboxd.com/film/drag-me-to-hell/"
  },
  "dreams in nightmares": {},
  "drowned land": {},
  "dry leaf": {
    "rating": 3.85,
    "slug": "dry-leaf",
    "url": "https://letterboxd.com/film/dry-leaf/"
  },
  "eastern promises": {},
  "ed wood": {
    "rating": 4.03,
    "slug": "ed-wood",
    "url": "https://letterboxd.com/film/ed-wood/"
  },
  "eight bridges": {
    "rating": null,
    "slug": "eight-bridges",
    "url": "https://letterboxd.com/film/eight-bridges/"
  },
  "el sur": {
    "rating": 4.16,
    "slug": "el-sur",
    "url": "https://letterboxd.com/film/el-sur/"
  },
  "emergencies": {},
  "emergency exits\n\n|  scrape\n\n|  project haunted house\n\n|  next tuesday\n\n|  seven vignettes: jan. 30 - sept. 15, 2025\n\n|  christ complex\n\n|  goodbye 2011\n\n|  trans american\n\n|  i too once lived in bushwick\n\n|  dual/visions\n\n|  apocalypse sunshine\n\n|  the thoughts": {},
  "emergent city": {
    "rating": 3.63,
    "slug": "emergent-city",
    "url": "https://letterboxd.com/film/emergent-city/"
  },
  "empire city": {},
  "empty suitcases": {},
  "end of days": {},
  "end of history": {},
  "enzo": {
    "rating": 3.09,
    "slug": "enzo-2025",
    "url": "https://letterboxd.com/film/enzo-2025/"
  },
  "eraserhead": {},
  "erupcja": {},
  "eternal sunshine of the spotless mind": {
    "rating": 4.24,
    "slug": "eternal-sunshine-of-the-spotless-mind",
    "url": "https://letterboxd.com/film/eternal-sunshine-of-the-spotless-mind/"
  },
  "eve's bayou": {},
  "everyone is lying to you for money": {},
  "excalibur": {
    "rating": 3.74,
    "slug": "excalibur",
    "url": "https://letterboxd.com/film/excalibur/"
  },
  "eyes without a face": {
    "rating": 3.92,
    "slug": "eyes-without-a-face",
    "url": "https://letterboxd.com/film/eyes-without-a-face/"
  },
  "f for fake": {
    "rating": 4.21,
    "slug": "f-for-fake",
    "url": "https://letterboxd.com/film/f-for-fake/"
  },
  "faces places": {
    "rating": 4.15,
    "slug": "faces-places",
    "url": "https://letterboxd.com/film/faces-places/"
  },
  "facing war": {
    "rating": 3.7,
    "slug": "facing-war",
    "url": "https://letterboxd.com/film/facing-war/"
  },
  "family nest": {
    "rating": 3.65,
    "slug": "family-nest",
    "url": "https://letterboxd.com/film/family-nest/"
  },
  "fanboy": {},
  "fanny and alexander": {
    "rating": 4.42,
    "slug": "fanny-and-alexander",
    "url": "https://letterboxd.com/film/fanny-and-alexander/"
  },
  "fantasia": {
    "rating": 3.91,
    "slug": "fantasia",
    "url": "https://letterboxd.com/film/fantasia/"
  },
  "fantastic voyage": {
    "rating": 3.41,
    "slug": "fantastic-voyage",
    "url": "https://letterboxd.com/film/fantastic-voyage/"
  },
  "fantasy": {},
  "far from poland": {
    "rating": null,
    "slug": "far-from-poland",
    "url": "https://letterboxd.com/film/far-from-poland/"
  },
  "fargo": {
    "rating": 4.15,
    "slug": "fargo",
    "url": "https://letterboxd.com/film/fargo/"
  },
  "fat girl": {
    "rating": 3.44,
    "slug": "fat-girl",
    "url": "https://letterboxd.com/film/fat-girl/"
  },
  "faust": {
    "rating": 4.14,
    "slug": "faust-1926",
    "url": "https://letterboxd.com/film/faust-1926/"
  },
  "female prisoner 701: scorpion": {
    "rating": 3.9,
    "slug": "female-prisoner-701-scorpion",
    "url": "https://letterboxd.com/film/female-prisoner-701-scorpion/"
  },
  "female prisoner scorpion: beast stable": {},
  "female prisoner scorpion: jailhouse 41": {
    "rating": 3.86,
    "slug": "female-prisoner-scorpion-jailhouse-41",
    "url": "https://letterboxd.com/film/female-prisoner-scorpion-jailhouse-41/"
  },
  "fight club": {},
  "film no. 12: heaven and earth magic": {},
  "final fantasy: the spirits within": {},
  "fiume o morte!": {},
  "flesh + blood": {
    "rating": 3.47,
    "slug": "flesh-blood-1985",
    "url": "https://letterboxd.com/film/flesh-blood-1985/"
  },
  "force majeure": {
    "rating": 3.88,
    "slug": "force-majeure-2014",
    "url": "https://letterboxd.com/film/force-majeure-2014/"
  },
  "forest high": {},
  "forward, soviet!": {},
  "four adventures of reinette and mirabelle": {
    "rating": 4.05,
    "slug": "four-adventures-of-reinette-and-mirabelle",
    "url": "https://letterboxd.com/film/four-adventures-of-reinette-and-mirabelle/"
  },
  "franju shorts": {},
  "frankenstein": {
    "rating": 3.84,
    "slug": "frankenstein-2025",
    "url": "https://letterboxd.com/film/frankenstein-2025/"
  },
  "franz": {
    "rating": 3.09,
    "slug": "franz-2025",
    "url": "https://letterboxd.com/film/franz-2025/"
  },
  "free time": {},
  "freeway": {},
  "friends of friends": {
    "rating": 3.51,
    "slug": "friends-of-friends-2002",
    "url": "https://letterboxd.com/film/friends-of-friends-2002/"
  },
  "frozen": {
    "rating": null,
    "slug": "their-frozen-dream",
    "url": "https://letterboxd.com/film/their-frozen-dream/"
  },
  "full metal jacket": {},
  "funny games": {},
  "future of documentary: secret screening & panel": {},
  "gabbeh": {
    "rating": 3.79,
    "slug": "gabbeh",
    "url": "https://letterboxd.com/film/gabbeh/"
  },
  "gaea girls": {
    "rating": 3.94,
    "slug": "gaea-girls",
    "url": "https://letterboxd.com/film/gaea-girls/"
  },
  "game changers": {
    "rating": 2.76,
    "slug": "game-changers-2024",
    "url": "https://letterboxd.com/film/game-changers-2024/"
  },
  "gentlemen prefer blondes": {
    "rating": 3.86,
    "slug": "gentlemen-prefer-blondes",
    "url": "https://letterboxd.com/film/gentlemen-prefer-blondes/"
  },
  "gently down the stream\n\n|  the ties that bind\n\n|  from a to z": {},
  "gh05+h4ck": {},
  "ghost dog: the way of the samurai": {},
  "ghost elephants": {},
  "ghost world": {
    "rating": 3.58,
    "slug": "ghost-world",
    "url": "https://letterboxd.com/film/ghost-world/"
  },
  "girls about town": {
    "rating": 3.48,
    "slug": "girls-about-town",
    "url": "https://letterboxd.com/film/girls-about-town/"
  },
  "god's gift": {},
  "gods and monsters": {},
  "good hot stuff": {
    "rating": null,
    "slug": "good-hot-stuff-1975",
    "url": "https://letterboxd.com/film/good-hot-stuff-1975/"
  },
  "goodbye horses: the many lives of q lazzarus": {},
  "goodbye, dragon inn": {
    "rating": 3.97,
    "slug": "goodbye-dragon-inn",
    "url": "https://letterboxd.com/film/goodbye-dragon-inn/"
  },
  "goodfellas": {},
  "gosford park": {
    "rating": 3.66,
    "slug": "gosford-park",
    "url": "https://letterboxd.com/film/gosford-park/"
  },
  "gowanus current": {},
  "greed": {},
  "guess who is calling?": {},
  "guru, the mad monk": {
    "rating": 2.6,
    "slug": "guru-the-mad-monk",
    "url": "https://letterboxd.com/film/guru-the-mad-monk/"
  },
  "haifa": {
    "rating": null,
    "slug": "haifa",
    "url": "https://letterboxd.com/film/haifa/"
  },
  "hank's saloon": {},
  "happy feet": {
    "rating": 3.05,
    "slug": "happy-feet",
    "url": "https://letterboxd.com/film/happy-feet/"
  },
  "harmonica": {},
  "harvest: 3,000 years": {},
  "hearts on fire": {},
  "hedwig and the angry inch": {},
  "heightened scrutiny": {},
  "high life": {
    "rating": 3.2,
    "slug": "high-life-2018",
    "url": "https://letterboxd.com/film/high-life-2018/"
  },
  "hollywood or bust": {
    "rating": 3.32,
    "slug": "hollywood-or-bust",
    "url": "https://letterboxd.com/film/hollywood-or-bust/"
  },
  "holy motors": {
    "rating": 3.9,
    "slug": "holy-motors",
    "url": "https://letterboxd.com/film/holy-motors/"
  },
  "home alone": {
    "rating": 3.85,
    "slug": "home-alone",
    "url": "https://letterboxd.com/film/home-alone/"
  },
  "horangi\n\n|  how should i film deer?\n\n|  midnight service\n\n|  chica gringa uruguaya\n\n|  born secret\n\n|  for stela": {},
  "horse feathers": {},
  "house": {
    "rating": 3.99,
    "slug": "house",
    "url": "https://letterboxd.com/film/house/"
  },
  "house show\n\n|  utopian wedding\n\n|  fields fallen from distant songs\n\n|  tourniquet\n\n|  the motherfucker's birthday\n\n|  while i read this letter": {},
  "how to marry a millionaire": {
    "rating": 3.48,
    "slug": "how-to-marry-a-millionaire",
    "url": "https://letterboxd.com/film/how-to-marry-a-millionaire/"
  },
  "hugo": {
    "rating": null,
    "slug": "official-hige-dandism-live-at-stadium-2025",
    "url": "https://letterboxd.com/film/official-hige-dandism-live-at-stadium-2025/"
  },
  "hundreds of beavers": {},
  "husbands": {
    "rating": 3.81,
    "slug": "husbands",
    "url": "https://letterboxd.com/film/husbands/"
  },
  "hustle & flow": {},
  "i am love": {
    "rating": 3.76,
    "slug": "i-am-love",
    "url": "https://letterboxd.com/film/i-am-love/"
  },
  "i can see the moon, and sometimes i wonder\n\n|  it's only love\n\n|  no more than anyone else": {},
  "i have graduated": {},
  "i just can't go on": {
    "rating": null,
    "slug": "i-just-cant-go-on",
    "url": "https://letterboxd.com/film/i-just-cant-go-on/"
  },
  "i live here now": {
    "rating": 3.05,
    "slug": "i-live-here-now",
    "url": "https://letterboxd.com/film/i-live-here-now/"
  },
  "i want to talk about duras": {
    "rating": 3.39,
    "slug": "i-want-to-talk-about-duras",
    "url": "https://letterboxd.com/film/i-want-to-talk-about-duras/"
  },
  "i'm going home": {
    "rating": 3.72,
    "slug": "im-going-home",
    "url": "https://letterboxd.com/film/im-going-home/"
  },
  "if on a winter's night": {},
  "imaginary zoo\n\n|  amusement park of beijing": {},
  "in a lonely place": {
    "rating": 4.2,
    "slug": "in-a-lonely-place",
    "url": "https://letterboxd.com/film/in-a-lonely-place/"
  },
  "in a whisper": {
    "rating": 3.54,
    "slug": "in-a-whisper-2026",
    "url": "https://letterboxd.com/film/in-a-whisper-2026/"
  },
  "in celebration of ken and flo jacobs": {},
  "in jackson heights": {},
  "in praise of love (\u00e9loge de l'amour)": {},
  "in the mood for love": {
    "rating": 4.38,
    "slug": "in-the-mood-for-love",
    "url": "https://letterboxd.com/film/in-the-mood-for-love/"
  },
  "in-i in motion": {
    "rating": 3.36,
    "slug": "in-i-in-motion",
    "url": "https://letterboxd.com/film/in-i-in-motion/"
  },
  "india song": {
    "rating": 3.7,
    "slug": "india-song",
    "url": "https://letterboxd.com/film/india-song/"
  },
  "indiana jones and the temple of doom": {},
  "inherent vice": {
    "rating": 3.61,
    "slug": "inherent-vice",
    "url": "https://letterboxd.com/film/inherent-vice/"
  },
  "inland empire": {
    "rating": 3.89,
    "slug": "inland-empire",
    "url": "https://letterboxd.com/film/inland-empire/"
  },
  "inside the yellow cocoon shell": {
    "rating": 3.63,
    "slug": "inside-the-yellow-cocoon-shell",
    "url": "https://letterboxd.com/film/inside-the-yellow-cocoon-shell/"
  },
  "invention for destruction": {},
  "iracema": {
    "rating": 3.73,
    "slug": "iracema",
    "url": "https://letterboxd.com/film/iracema/"
  },
  "irma vep": {
    "rating": 3.9,
    "slug": "irma-vep",
    "url": "https://letterboxd.com/film/irma-vep/"
  },
  "it was just an accident": {
    "rating": 3.98,
    "slug": "it-was-just-an-accident",
    "url": "https://letterboxd.com/film/it-was-just-an-accident/"
  },
  "jacquot de nantes": {
    "rating": 4.16,
    "slug": "jacquot-de-nantes",
    "url": "https://letterboxd.com/film/jacquot-de-nantes/"
  },
  "jane b. by agn\u00e8s v.": {
    "rating": 4.0,
    "slug": "jane-b-by-agnes-v",
    "url": "https://letterboxd.com/film/jane-b-by-agnes-v/"
  },
  "jawbreaker": {
    "rating": 3.41,
    "slug": "jawbreaker",
    "url": "https://letterboxd.com/film/jawbreaker/"
  },
  "jaws": {
    "rating": 3.93,
    "slug": "jaws",
    "url": "https://letterboxd.com/film/jaws/"
  },
  "jerry takes a back seat, then passes out of the picture\n\n|  urban peasants": {},
  "john lilly and the earth coincidence control office": {
    "rating": 3.39,
    "slug": "john-lilly-and-the-earth-coincidence-control",
    "url": "https://letterboxd.com/film/john-lilly-and-the-earth-coincidence-control/"
  },
  "ju dou": {
    "rating": 3.82,
    "slug": "ju-dou",
    "url": "https://letterboxd.com/film/ju-dou/"
  },
  "judex": {
    "rating": 3.62,
    "slug": "judex-1963",
    "url": "https://letterboxd.com/film/judex-1963/"
  },
  "keep your right up / soigne ta droite": {},
  "ken jacobs's lower east side: a tribute": {},
  "kika": {},
  "kill bill: vol. 1": {
    "rating": 4.21,
    "slug": "kill-bill-vol-1",
    "url": "https://letterboxd.com/film/kill-bill-vol-1/"
  },
  "kill bill: vol. 2": {
    "rating": 4.1,
    "slug": "kill-bill-vol-2",
    "url": "https://letterboxd.com/film/kill-bill-vol-2/"
  },
  "king lear": {},
  "kino-eye": {},
  "kino-pravda, nos. 1-6": {},
  "kiss me deadly": {
    "rating": 3.99,
    "slug": "kiss-me-deadly",
    "url": "https://letterboxd.com/film/kiss-me-deadly/"
  },
  "klute": {
    "rating": 3.86,
    "slug": "klute",
    "url": "https://letterboxd.com/film/klute/"
  },
  "kontinental \u201825": {
    "rating": 3.53,
    "slug": "kontinental-25",
    "url": "https://letterboxd.com/film/kontinental-25/"
  },
  "krabi 2562\n\n|  the ambassador": {},
  "kung-fu master!": {},
  "la notte": {},
  "la pointe courte": {
    "rating": 3.71,
    "slug": "la-pointe-courte",
    "url": "https://letterboxd.com/film/la-pointe-courte/"
  },
  "la ronde": {
    "rating": 3.9,
    "slug": "la-ronde",
    "url": "https://letterboxd.com/film/la-ronde/"
  },
  "labyrinth": {
    "rating": 3.76,
    "slug": "labyrinth",
    "url": "https://letterboxd.com/film/labyrinth/"
  },
  "lady snowblood": {
    "rating": 4.11,
    "slug": "lady-snowblood",
    "url": "https://letterboxd.com/film/lady-snowblood/"
  },
  "las madres: the mothers of plaza de mayo": {
    "rating": 3.69,
    "slug": "the-mothers-of-plaza-de-mayo",
    "url": "https://letterboxd.com/film/the-mothers-of-plaza-de-mayo/"
  },
  "laserblast": {
    "rating": 2.15,
    "slug": "laserblast",
    "url": "https://letterboxd.com/film/laserblast/"
  },
  "last year at marienbad": {
    "rating": 4.1,
    "slug": "last-year-at-marienbad",
    "url": "https://letterboxd.com/film/last-year-at-marienbad/"
  },
  "late autumn": {
    "rating": 4.12,
    "slug": "late-autumn",
    "url": "https://letterboxd.com/film/late-autumn/"
  },
  "lawrence of arabia": {
    "rating": 4.4,
    "slug": "lawrence-of-arabia",
    "url": "https://letterboxd.com/film/lawrence-of-arabia/"
  },
  "le bonheur": {
    "rating": 4.14,
    "slug": "happiness-1965",
    "url": "https://letterboxd.com/film/happiness-1965/"
  },
  "le plaisir": {
    "rating": 3.93,
    "slug": "le-plaisir",
    "url": "https://letterboxd.com/film/le-plaisir/"
  },
  "leprechaun": {
    "rating": 2.36,
    "slug": "leprechaun",
    "url": "https://letterboxd.com/film/leprechaun/"
  },
  "les cr\u00e9atures (the creatures)": {},
  "les fant\u00f4mes du hard 2\n\n|  please hold": {},
  "les hautes solitudes": {},
  "let the sunshine in": {
    "rating": 3.25,
    "slug": "let-the-sunshine-in",
    "url": "https://letterboxd.com/film/let-the-sunshine-in/"
  },
  "let's make love": {
    "rating": 3.24,
    "slug": "lets-make-love",
    "url": "https://letterboxd.com/film/lets-make-love/"
  },
  "leviticus": {},
  "libert\u00e9, la nuit": {},
  "like crazy": {},
  "lioness (emal\u00f5vi)": {
    "rating": 3.5,
    "slug": "lioness-2024",
    "url": "https://letterboxd.com/film/lioness-2024/"
  },
  "lions love (... and lies)": {},
  "little nicky": {},
  "live-action oscar-nominated shorts 2026": {},
  "living in oblivion": {},
  "living the land": {},
  "lola mont\u00e8s": {
    "rating": 3.94,
    "slug": "lola-montes",
    "url": "https://letterboxd.com/film/lola-montes/"
  },
  "looking for you looking for me\n\n|  i was there\n\n|  is this now the time i should let you go?\n\n|  night flower\n\n|  accursed effigy\n\n|  b. longing\n\n|  this cycle that was passed down to me\n\n|  diary: setagaya angler\n\n|  rigmarole": {},
  "lost in translation": {},
  "love bird\n\n|  when all the shadows disappeared\n\n|  death tape\n\n|  dust we can\u2019t quite catch\n\n|  all day, and all of the night\n\n|  dark blue tones shade the teeth": {},
  "love jones": {},
  "love me tender": {
    "rating": 3.6,
    "slug": "love-me-tender-2025",
    "url": "https://letterboxd.com/film/love-me-tender-2025/"
  },
  "lumi\u00e8re, le cin\u00e9ma!": {},
  "lvira notari: beyond silence": {},
  "l\u2019op\u00e9ra-mouffe and other shorts": {},
  "mabou mines dollhouse": {},
  "mabou mines' lear '87 archive\n\n|": {
    "rating": null,
    "slug": "mabou-mines-lear-87-archive-condensed",
    "url": "https://letterboxd.com/film/mabou-mines-lear-87-archive-condensed/"
  },
  "mad bills to pay (or destiny, dile que no soy malo)": {},
  "maddie's secret": {},
  "made in hong kong": {
    "rating": 4.12,
    "slug": "made-in-hong-kong",
    "url": "https://letterboxd.com/film/made-in-hong-kong/"
  },
  "made in u.s.a.": {},
  "madonna: truth or dare": {
    "rating": 3.77,
    "slug": "madonna-truth-or-dare",
    "url": "https://letterboxd.com/film/madonna-truth-or-dare/"
  },
  "magellan": {},
  "maidan": {
    "rating": 3.53,
    "slug": "maidan",
    "url": "https://letterboxd.com/film/maidan/"
  },
  "maigret and the dead lover": {},
  "mala noche": {
    "rating": 3.26,
    "slug": "mala-noche",
    "url": "https://letterboxd.com/film/mala-noche/"
  },
  "malcolm x": {
    "rating": 4.28,
    "slug": "malcolm-x-1992",
    "url": "https://letterboxd.com/film/malcolm-x-1992/"
  },
  "maps to the stars": {
    "rating": 3.31,
    "slug": "maps-to-the-stars",
    "url": "https://letterboxd.com/film/maps-to-the-stars/"
  },
  "marama": {},
  "marc by sofia": {
    "rating": 3.25,
    "slug": "marc-by-sofia",
    "url": "https://letterboxd.com/film/marc-by-sofia/"
  },
  "married to the mob": {
    "rating": 3.47,
    "slug": "married-to-the-mob",
    "url": "https://letterboxd.com/film/married-to-the-mob/"
  },
  "marseille, 14th july\n\n|  division\n\n|  the following day\n\n|  time to go\n\n|  unleaded 95": {},
  "marty supreme": {
    "rating": 4.15,
    "slug": "marty-supreme",
    "url": "https://letterboxd.com/film/marty-supreme/"
  },
  "mastalghia\n\n|  stuck in the '90s": {},
  "matter of britain": {
    "rating": null,
    "slug": "matter-of-britain",
    "url": "https://letterboxd.com/film/matter-of-britain/"
  },
  "mauvais sang": {
    "rating": 3.95,
    "slug": "mauvais-sang",
    "url": "https://letterboxd.com/film/mauvais-sang/"
  },
  "melancholia": {
    "rating": 3.84,
    "slug": "melancholia",
    "url": "https://letterboxd.com/film/melancholia/"
  },
  "memento": {
    "rating": 4.18,
    "slug": "memento",
    "url": "https://letterboxd.com/film/memento/"
  },
  "memoria": {
    "rating": 3.77,
    "slug": "memoria-2021",
    "url": "https://letterboxd.com/film/memoria-2021/"
  },
  "memory": {},
  "memory garden\n\n|  colorado\n\n|  i would've been happy\n\n|  padre nuestro\n\n|  i love you so much but you are so difficult\n\n|  the angie archive": {},
  "messengers": {},
  "meteors": {
    "rating": 3.23,
    "slug": "meteors-2025-1",
    "url": "https://letterboxd.com/film/meteors-2025-1/"
  },
  "miami vice": {},
  "michael clayton": {},
  "microcosmos": {},
  "midnight run": {},
  "mikey and nicky": {
    "rating": 4.07,
    "slug": "mikey-and-nicky",
    "url": "https://letterboxd.com/film/mikey-and-nicky/"
  },
  "millennium mambo": {
    "rating": 3.83,
    "slug": "millennium-mambo",
    "url": "https://letterboxd.com/film/millennium-mambo/"
  },
  "miriam: home delivery": {
    "rating": null,
    "slug": "miriam-home-delivery",
    "url": "https://letterboxd.com/film/miriam-home-delivery/"
  },
  "miroirs no. 3": {},
  "misery": {
    "rating": 3.99,
    "slug": "misery",
    "url": "https://letterboxd.com/film/misery/"
  },
  "miss mend": {
    "rating": 3.55,
    "slug": "miss-mend",
    "url": "https://letterboxd.com/film/miss-mend/"
  },
  "modern romance": {
    "rating": 3.73,
    "slug": "modern-romance",
    "url": "https://letterboxd.com/film/modern-romance/"
  },
  "moi-m\u00eame": {
    "rating": null,
    "slug": "moi-meme",
    "url": "https://letterboxd.com/film/moi-meme/"
  },
  "money from home": {
    "rating": 3.24,
    "slug": "money-from-home",
    "url": "https://letterboxd.com/film/money-from-home/"
  },
  "monkey business": {
    "rating": 3.45,
    "slug": "monkey-business-1952",
    "url": "https://letterboxd.com/film/monkey-business-1952/"
  },
  "monsters, inc.": {
    "rating": 4.08,
    "slug": "monsters-inc",
    "url": "https://letterboxd.com/film/monsters-inc/"
  },
  "monte carlo": {},
  "monty python and the holy grail": {},
  "more beautiful perversions": {},
  "morichales": {
    "rating": null,
    "slug": "morichales",
    "url": "https://letterboxd.com/film/morichales/"
  },
  "mother of snow cranes": {
    "rating": null,
    "slug": "mother-of-snow-cranes",
    "url": "https://letterboxd.com/film/mother-of-snow-cranes/"
  },
  "mouse hunt": {
    "rating": 3.29,
    "slug": "mousehunt",
    "url": "https://letterboxd.com/film/mousehunt/"
  },
  "mr. nobody against putin": {
    "rating": 3.7,
    "slug": "mr-nobody-against-putin",
    "url": "https://letterboxd.com/film/mr-nobody-against-putin/"
  },
  "mulholland dr.": {
    "rating": 4.26,
    "slug": "mulholland-drive",
    "url": "https://letterboxd.com/film/mulholland-drive/"
  },
  "mulholland drive": {
    "rating": 4.26,
    "slug": "mulholland-drive",
    "url": "https://letterboxd.com/film/mulholland-drive/"
  },
  "mundane history": {
    "rating": 3.67,
    "slug": "mundane-history",
    "url": "https://letterboxd.com/film/mundane-history/"
  },
  "mur murs": {},
  "murray center class of '25: award-winning shorts": {},
  "musica quarantena\n\n|  gloria\n\n|  shallow end\n\n|  laundry\n\n|  the knife\n\n|  superman doesn't steal": {},
  "my life as a zucchini": {},
  "my sunny maad\n\n|  repete": {},
  "mysterious object at noon (dokfa nai meuman)": {},
  "naked lunch": {
    "rating": 3.76,
    "slug": "naked-lunch",
    "url": "https://letterboxd.com/film/naked-lunch/"
  },
  "narrative\n\n|  local sensations": {},
  "natchez": {
    "rating": 4.03,
    "slug": "natchez-2025",
    "url": "https://letterboxd.com/film/natchez-2025/"
  },
  "nausicaa": {
    "rating": 3.48,
    "slug": "nausicaa",
    "url": "https://letterboxd.com/film/nausicaa/"
  },
  "nausica\u00e4 of the valley of the wind": {},
  "near dark": {
    "rating": 3.53,
    "slug": "near-dark",
    "url": "https://letterboxd.com/film/near-dark/"
  },
  "neighboring animals\n\n|  clever hans\n\n|  figure minus fact\n\n|  the glass note \n\n|  exhibition": {},
  "new battles without honor and humanity: the boss\u2019s head": {},
  "new york ghetto fishmarket 1903": {},
  "new york, ny\n\n|  reporters": {},
  "news items": {
    "rating": 3.68,
    "slug": "news-items",
    "url": "https://letterboxd.com/film/news-items/"
  },
  "next life": {},
  "niagra": {},
  "night of the creeps": {
    "rating": 3.5,
    "slug": "night-of-the-creeps",
    "url": "https://letterboxd.com/film/night-of-the-creeps/"
  },
  "night of the living dead": {
    "rating": 3.94,
    "slug": "night-of-the-living-dead",
    "url": "https://letterboxd.com/film/night-of-the-living-dead/"
  },
  "nighthawks": {},
  "nino": {
    "rating": 3.82,
    "slug": "nino-2025",
    "url": "https://letterboxd.com/film/nino-2025/"
  },
  "nirvanna: the band the show the movie": {},
  "no country for old men": {},
  "no other choice": {
    "rating": 4.09,
    "slug": "no-other-choice-2025",
    "url": "https://letterboxd.com/film/no-other-choice-2025/"
  },
  "no president": {},
  "noli me tangere\n\n|  las ma\u00f1anitas\n\n|  getting to know you again\n\n|  formosa\n\n|  true or real\n\n|  gu-neon / nine years\n\n|  always/never (together forever)\n\n|  from here\n\n|  whales": {},
  "nor any memories of the turning backs\n\n|  eurydice in the underworld\n\n|  milwaukee night and day\n\n|  between the sky and earth\n\n|  bozos on the bus\n\n|  rahhala: hayya ala hayya": {},
  "noroi: the curse": {},
  "nostalghia": {
    "rating": 4.28,
    "slug": "nostalgia-1983",
    "url": "https://letterboxd.com/film/nostalgia-1983/"
  },
  "notes from beijing": {},
  "nouvelle vague": {
    "rating": 3.62,
    "slug": "nouvelle-vague",
    "url": "https://letterboxd.com/film/nouvelle-vague/"
  },
  "nova '78": {
    "rating": 3.43,
    "slug": "nova-78",
    "url": "https://letterboxd.com/film/nova-78/"
  },
  "nuits rouges": {},
  "numbskull revolution": {
    "rating": null,
    "slug": "numbskull-revolution",
    "url": "https://letterboxd.com/film/numbskull-revolution/"
  },
  "old georgian hymns\n\n|  ancient georgian songs": {},
  "omar": {
    "rating": 3.79,
    "slug": "omar",
    "url": "https://letterboxd.com/film/omar/"
  },
  "on what continent is the country amnesia?\n\n|  flattening billionaires is my passion!\n\n|  dextra_1\n\n|  the boy was found unharmed\n\n|  object permanence\n\n|  like a tongue knows the mouth": {},
  "once upon a night\n\n|  a priceless head": {},
  "once upon a time... in hollywood": {
    "rating": 3.76,
    "slug": "once-upon-a-time-in-hollywood",
    "url": "https://letterboxd.com/film/once-upon-a-time-in-hollywood/"
  },
  "one hundred and one nights": {
    "rating": 3.77,
    "slug": "one-hundred-and-one-nights",
    "url": "https://letterboxd.com/film/one-hundred-and-one-nights/"
  },
  "one sings, the other doesn't": {
    "rating": 4.14,
    "slug": "one-sings-the-other-doesnt",
    "url": "https://letterboxd.com/film/one-sings-the-other-doesnt/"
  },
  "other children\n\n|  dead end kids: a history of nuclear power": {},
  "our demand": {},
  "out of sight": {},
  "outcome": {},
  "outskirts": {
    "rating": 3.65,
    "slug": "outskirts",
    "url": "https://letterboxd.com/film/outskirts/"
  },
  "palestine 36": {
    "rating": 3.85,
    "slug": "palestine-36",
    "url": "https://letterboxd.com/film/palestine-36/"
  },
  "panda": {},
  "paris": {
    "rating": 3.45,
    "slug": "paris-1900",
    "url": "https://letterboxd.com/film/paris-1900/"
  },
  "paris, texas": {
    "rating": 4.37,
    "slug": "paris-texas",
    "url": "https://letterboxd.com/film/paris-texas/"
  },
  "partner\n\n|  jakob il reale e sosia il vero": {},
  "pauline at the beach": {},
  "peacemaker": {
    "rating": 3.75,
    "slug": "peacemaker-2025",
    "url": "https://letterboxd.com/film/peacemaker-2025/"
  },
  "peaky blinders: the immortal man": {
    "rating": null,
    "slug": "peaky-blinders-the-immortal-man",
    "url": "https://letterboxd.com/film/peaky-blinders-the-immortal-man/"
  },
  "perfect blue": {
    "rating": 4.38,
    "slug": "perfect-blue",
    "url": "https://letterboxd.com/film/perfect-blue/"
  },
  "perfect film\n\n|  capitalism: slavery \n\n|  what happened on 23rd street in 1901\n\n|  gift of fire: nineteen (obscure) frames that changed the world": {},
  "phantom thread": {},
  "pictures of ghosts": {
    "rating": 3.89,
    "slug": "pictures-of-ghosts",
    "url": "https://letterboxd.com/film/pictures-of-ghosts/"
  },
  "pieces of april": {
    "rating": 3.64,
    "slug": "pieces-of-april",
    "url": "https://letterboxd.com/film/pieces-of-april/"
  },
  "pierrot le fou": {
    "rating": 4.03,
    "slug": "pierrot-le-fou",
    "url": "https://letterboxd.com/film/pierrot-le-fou/"
  },
  "pinocchio": {
    "rating": 3.47,
    "slug": "pinocchio",
    "url": "https://letterboxd.com/film/pinocchio/"
  },
  "planet of the apes": {},
  "point blank": {
    "rating": 3.91,
    "slug": "point-blank",
    "url": "https://letterboxd.com/film/point-blank/"
  },
  "pompei: below the clouds": {
    "rating": 3.45,
    "slug": "pompei-below-the-clouds",
    "url": "https://letterboxd.com/film/pompei-below-the-clouds/"
  },
  "portrait of a lady on fire": {
    "rating": 4.42,
    "slug": "portrait-of-a-lady-on-fire",
    "url": "https://letterboxd.com/film/portrait-of-a-lady-on-fire/"
  },
  "possession": {
    "rating": 4.04,
    "slug": "possession",
    "url": "https://letterboxd.com/film/possession/"
  },
  "powwow people": {
    "rating": null,
    "slug": "powwow-people",
    "url": "https://letterboxd.com/film/powwow-people/"
  },
  "projection": {
    "rating": null,
    "slug": "the-projectionist-2026",
    "url": "https://letterboxd.com/film/the-projectionist-2026/"
  },
  "provincial actors": {},
  "public housing": {
    "rating": 4.04,
    "slug": "public-housing",
    "url": "https://letterboxd.com/film/public-housing/"
  },
  "puddysticks": {},
  "pulp fiction": {
    "rating": 4.24,
    "slug": "pulp-fiction",
    "url": "https://letterboxd.com/film/pulp-fiction/"
  },
  "pulse": {
    "rating": 3.69,
    "slug": "pulse-2001",
    "url": "https://letterboxd.com/film/pulse-2001/"
  },
  "punch-drunk love": {
    "rating": 3.96,
    "slug": "punch-drunk-love",
    "url": "https://letterboxd.com/film/punch-drunk-love/"
  },
  "pyjama girls": {
    "rating": null,
    "slug": "pyjama-girls",
    "url": "https://letterboxd.com/film/pyjama-girls/"
  },
  "queen of katwe": {
    "rating": 3.64,
    "slug": "queen-of-katwe",
    "url": "https://letterboxd.com/film/queen-of-katwe/"
  },
  "queen of the damned": {},
  "quelques veuves de noirmoutier": {
    "rating": 3.63,
    "slug": "some-widows-of-noirmoutier",
    "url": "https://letterboxd.com/film/some-widows-of-noirmoutier/"
  },
  "racetrack": {
    "rating": 3.48,
    "slug": "racetrack",
    "url": "https://letterboxd.com/film/racetrack/"
  },
  "raise the red lantern": {
    "rating": 4.34,
    "slug": "raise-the-red-lantern",
    "url": "https://letterboxd.com/film/raise-the-red-lantern/"
  },
  "ran": {
    "rating": 4.51,
    "slug": "ran",
    "url": "https://letterboxd.com/film/ran/"
  },
  "ratatouille": {
    "rating": 4.23,
    "slug": "ratatouille",
    "url": "https://letterboxd.com/film/ratatouille/"
  },
  "re-wind": {},
  "real life": {},
  "red code blue": {
    "rating": 3.78,
    "slug": "red-code-blue",
    "url": "https://letterboxd.com/film/red-code-blue/"
  },
  "red sorghum": {},
  "reeling": {},
  "remake": {
    "rating": 3.87,
    "slug": "remake-2025",
    "url": "https://letterboxd.com/film/remake-2025/"
  },
  "remote views\n\n|  i'm not jean-luc godard\n\n|  persistence of memory (blue)\n\n|  google search history\n\n|  the year\n\n|  typhoon diary\n\n|  this is how i felt\n\n|  black sheep:brown eyes \u1325\u1241\u122d \u1260\u130d : \u1261\u1293\u121b \u12a0\u12ed\u1296\u127d\n\n|  oblivion": {},
  "rendez-vous": {
    "rating": 3.11,
    "slug": "rendez-vous",
    "url": "https://letterboxd.com/film/rendez-vous/"
  },
  "resilience": {
    "rating": null,
    "slug": "resilience-2025",
    "url": "https://letterboxd.com/film/resilience-2025/"
  },
  "resurrection": {},
  "resurrection of eve": {
    "rating": null,
    "slug": "resurrection-of-eve",
    "url": "https://letterboxd.com/film/resurrection-of-eve/"
  },
  "reunion": {},
  "revelations of divine love": {
    "rating": null,
    "slug": "revelations-of-divine-love",
    "url": "https://letterboxd.com/film/revelations-of-divine-love/"
  },
  "revolutionary road": {},
  "richard iii": {
    "rating": null,
    "slug": "richard-iii-1986",
    "url": "https://letterboxd.com/film/richard-iii-1986/"
  },
  "riding in cars with boys": {
    "rating": 3.49,
    "slug": "riding-in-cars-with-boys",
    "url": "https://letterboxd.com/film/riding-in-cars-with-boys/"
  },
  "river of no return": {
    "rating": 3.2,
    "slug": "river-of-no-return",
    "url": "https://letterboxd.com/film/river-of-no-return/"
  },
  "river's edge": {},
  "robert wilson and the civil wars": {},
  "roberto baggio\n\n|  bosnian war movie\n\n|  alienation in the time of eschatology\n\n|  to be eighteen (the war)\n\n|  closure\n\n|  qirim\n\n|  about the pain of others\n\n|  junior tu pap\u00e1": {},
  "rosemary's baby": {
    "rating": 4.21,
    "slug": "rosemarys-baby",
    "url": "https://letterboxd.com/film/rosemarys-baby/"
  },
  "rosemead": {
    "rating": 3.49,
    "slug": "rosemead",
    "url": "https://letterboxd.com/film/rosemead/"
  },
  "s:tream:s:s:ection:s:ection:s:s:ectioned\n\n|  color sound frames": {},
  "sambizanga": {
    "rating": 3.85,
    "slug": "sambizanga",
    "url": "https://letterboxd.com/film/sambizanga/"
  },
  "satan's bed": {},
  "scarface": {
    "rating": 4.14,
    "slug": "scarface-1983",
    "url": "https://letterboxd.com/film/scarface-1983/"
  },
  "scenes from the divide": {
    "rating": null,
    "slug": "scenes-from-the-divide",
    "url": "https://letterboxd.com/film/scenes-from-the-divide/"
  },
  "scotch tape\n\n|  flaming creatures\n\n|  chumlum": {},
  "scotch tape\n\n|  skeleton dance\n\n|  blue moses\n\n|  unsere afrikareise\n\n|  airshaft\n\n|  wait\n\n|  calling all girls": {},
  "screwdriver": {
    "rating": null,
    "slug": "screwdriver",
    "url": "https://letterboxd.com/film/screwdriver/"
  },
  "secret agent": {
    "rating": null,
    "slug": "secret-agent-1947",
    "url": "https://letterboxd.com/film/secret-agent-1947/"
  },
  "secrets & lies": {},
  "serpent's path\n\n|  chime": {},
  "set it off": {
    "rating": 3.74,
    "slug": "set-it-off",
    "url": "https://letterboxd.com/film/set-it-off/"
  },
  "sexmission": {},
  "shanghai dreams": {
    "rating": 3.54,
    "slug": "shanghai-dreams",
    "url": "https://letterboxd.com/film/shanghai-dreams/"
  },
  "shanghai triad": {},
  "shattered glass": {
    "rating": 3.42,
    "slug": "shattered-glass",
    "url": "https://letterboxd.com/film/shattered-glass/"
  },
  "she mob": {
    "rating": 3.06,
    "slug": "she-mob",
    "url": "https://letterboxd.com/film/she-mob/"
  },
  "sherlock jr.\n\n|  one week": {},
  "shoes": {
    "rating": 3.63,
    "slug": "shoes",
    "url": "https://letterboxd.com/film/shoes/"
  },
  "show me love": {
    "rating": 3.78,
    "slug": "show-me-love",
    "url": "https://letterboxd.com/film/show-me-love/"
  },
  "showgirls": {
    "rating": 3.45,
    "slug": "showgirls",
    "url": "https://letterboxd.com/film/showgirls/"
  },
  "silsila": {
    "rating": 3.36,
    "slug": "silsila",
    "url": "https://letterboxd.com/film/silsila/"
  },
  "silvia prieto": {
    "rating": 3.65,
    "slug": "silvia-prieto",
    "url": "https://letterboxd.com/film/silvia-prieto/"
  },
  "sir\u0101t": {
    "rating": 3.54,
    "slug": "sirat-2025",
    "url": "https://letterboxd.com/film/sirat-2025/"
  },
  "smile at last": {
    "rating": 3.68,
    "slug": "smile-at-last",
    "url": "https://letterboxd.com/film/smile-at-last/"
  },
  "smithereens": {
    "rating": 3.57,
    "slug": "smithereens",
    "url": "https://letterboxd.com/film/smithereens/"
  },
  "smorgasbord": {
    "rating": 3.59,
    "slug": "smorgasbord",
    "url": "https://letterboxd.com/film/smorgasbord/"
  },
  "snow white and the seven dwarfs": {
    "rating": 3.42,
    "slug": "snow-white-and-the-seven-dwarfs",
    "url": "https://letterboxd.com/film/snow-white-and-the-seven-dwarfs/"
  },
  "snowy bing bongs": {},
  "soft exit wound\n\n|  more of a circle\n\n|  nestor drank too much milk and vomited at the gloryhole\n\n|  cytokine storm\n\n|  ignore your true feelings at your own peril\n\n|  autobiography of my diabetes": {},
  "softshell": {
    "rating": 3.63,
    "slug": "softshell",
    "url": "https://letterboxd.com/film/softshell/"
  },
  "sole survivor": {
    "rating": 3.34,
    "slug": "sole-survivor-1984",
    "url": "https://letterboxd.com/film/sole-survivor-1984/"
  },
  "solomon northup's odyssey": {},
  "some eternal postcards\n\n|  dragking highway\n\n|  the roadtrip\n\n|  half halt\n\n|  odyssey\n\n|  family video 2024\n\n|  watch with the weary ones\n\n|  thank you, stillman\n\n|  the interior frontier": {},
  "some like it hot": {
    "rating": 4.27,
    "slug": "some-like-it-hot",
    "url": "https://letterboxd.com/film/some-like-it-hot/"
  },
  "somersault": {
    "rating": 3.41,
    "slug": "somersault",
    "url": "https://letterboxd.com/film/somersault/"
  },
  "something better change": {
    "rating": null,
    "slug": "something-better-change",
    "url": "https://letterboxd.com/film/something-better-change/"
  },
  "something to remind me": {
    "rating": 3.78,
    "slug": "something-to-remind-me",
    "url": "https://letterboxd.com/film/something-to-remind-me/"
  },
  "something very bad is going to happen, episode one": {},
  "sorrows": {
    "rating": null,
    "slug": "sorrows-2023",
    "url": "https://letterboxd.com/film/sorrows-2023/"
  },
  "southern comfort": {
    "rating": 4.14,
    "slug": "southern-comfort-2001",
    "url": "https://letterboxd.com/film/southern-comfort-2001/"
  },
  "space cowboy": {},
  "space is the place": {
    "rating": 3.7,
    "slug": "space-is-the-place",
    "url": "https://letterboxd.com/film/space-is-the-place/"
  },
  "spawn": {},
  "spotlight on a murderer": {
    "rating": 3.36,
    "slug": "spotlight-on-a-murderer",
    "url": "https://letterboxd.com/film/spotlight-on-a-murderer/"
  },
  "spring in the forest": {
    "rating": null,
    "slug": "spring-in-the-forest",
    "url": "https://letterboxd.com/film/spring-in-the-forest/"
  },
  "spy": {},
  "stairway to the distant past": {
    "rating": 3.65,
    "slug": "the-stairway-to-the-distant-past",
    "url": "https://letterboxd.com/film/the-stairway-to-the-distant-past/"
  },
  "stalker": {
    "rating": 4.4,
    "slug": "stalker",
    "url": "https://letterboxd.com/film/stalker/"
  },
  "stand by me": {},
  "star spangled to death": {
    "rating": 3.72,
    "slug": "star-spangled-to-death",
    "url": "https://letterboxd.com/film/star-spangled-to-death/"
  },
  "star wars: revenge of the sith": {
    "rating": 4.05,
    "slug": "star-wars-episode-iii-revenge-of-the-sith",
    "url": "https://letterboxd.com/film/star-wars-episode-iii-revenge-of-the-sith/"
  },
  "steal this story, please!": {},
  "strange brew": {},
  "strange river": {},
  "stranger and the fog": {
    "rating": 3.96,
    "slug": "the-stranger-and-the-fog",
    "url": "https://letterboxd.com/film/the-stranger-and-the-fog/"
  },
  "stranger by the lake": {
    "rating": 3.64,
    "slug": "stranger-by-the-lake",
    "url": "https://letterboxd.com/film/stranger-by-the-lake/"
  },
  "stray cat rock: beat '71": {},
  "stray cat rock: machine animal": {},
  "stray cat rock: sex hunter": {
    "rating": 3.33,
    "slug": "stray-cat-rock-sex-hunter",
    "url": "https://letterboxd.com/film/stray-cat-rock-sex-hunter/"
  },
  "sudden outbursts of emotions": {},
  "sugar cane alley": {
    "rating": 3.85,
    "slug": "sugar-cane-alley",
    "url": "https://letterboxd.com/film/sugar-cane-alley/"
  },
  "sugar island\n\n|  hija de florinda (florinda\u2019s daughter)": {},
  "sukiyaki western django": {
    "rating": 3.15,
    "slug": "sukiyaki-western-django",
    "url": "https://letterboxd.com/film/sukiyaki-western-django/"
  },
  "summer in the city": {},
  "summer school, 2001": {
    "rating": 3.71,
    "slug": "summer-school-2001",
    "url": "https://letterboxd.com/film/summer-school-2001/"
  },
  "sunday in peking\n\n|  sans soleil": {},
  "sunset boulevard": {
    "rating": 4.43,
    "slug": "sunset-boulevard",
    "url": "https://letterboxd.com/film/sunset-boulevard/"
  },
  "super mario bros.": {
    "rating": 2.13,
    "slug": "super-mario-bros",
    "url": "https://letterboxd.com/film/super-mario-bros/"
  },
  "suspiria": {
    "rating": 3.92,
    "slug": "suspiria",
    "url": "https://letterboxd.com/film/suspiria/"
  },
  "suzaki paradise": {},
  "swordfish": {
    "rating": 2.75,
    "slug": "swordfish",
    "url": "https://letterboxd.com/film/swordfish/"
  },
  "s\u00e1t\u00e1ntang\u00f3": {
    "rating": 4.39,
    "slug": "satantango",
    "url": "https://letterboxd.com/film/satantango/"
  },
  "taking of pelham 123": {},
  "talk radio": {
    "rating": 3.75,
    "slug": "talk-radio",
    "url": "https://letterboxd.com/film/talk-radio/"
  },
  "taxi driver": {},
  "teddy, out of tune": {
    "rating": null,
    "slug": "teddy-out-of-tune",
    "url": "https://letterboxd.com/film/teddy-out-of-tune/"
  },
  "teenage mutant ninja turtles": {},
  "that old dream that moves": {},
  "the #7 train: an immigrant journey\n\n|  down in shadowland": {},
  "the 10th district court \u2014 moments of trials": {},
  "the 400 blows": {},
  "the 5000 fingers of dr. t": {
    "rating": 3.47,
    "slug": "the-5000-fingers-of-dr-t",
    "url": "https://letterboxd.com/film/the-5000-fingers-of-dr-t/"
  },
  "the activist": {
    "rating": 2.92,
    "slug": "the-activist-2025",
    "url": "https://letterboxd.com/film/the-activist-2025/"
  },
  "the adventures of robin hood": {
    "rating": 3.86,
    "slug": "the-adventures-of-robin-hood",
    "url": "https://letterboxd.com/film/the-adventures-of-robin-hood/"
  },
  "the alabama solution": {
    "rating": 4.16,
    "slug": "the-alabama-solution",
    "url": "https://letterboxd.com/film/the-alabama-solution/"
  },
  "the alien agenda: out of the darkness": {},
  "the bad and the beautiful": {
    "rating": 3.99,
    "slug": "the-bad-and-the-beautiful",
    "url": "https://letterboxd.com/film/the-bad-and-the-beautiful/"
  },
  "the beaches of agn\u00e8s": {
    "rating": 4.33,
    "slug": "the-beaches-of-agnes",
    "url": "https://letterboxd.com/film/the-beaches-of-agnes/"
  },
  "the bellboy": {
    "rating": 3.51,
    "slug": "the-bellboy",
    "url": "https://letterboxd.com/film/the-bellboy/"
  },
  "the bigamist": {
    "rating": 3.52,
    "slug": "the-bigamist",
    "url": "https://letterboxd.com/film/the-bigamist/"
  },
  "the blue caftan": {
    "rating": 3.88,
    "slug": "the-blue-caftan",
    "url": "https://letterboxd.com/film/the-blue-caftan/"
  },
  "the blue trail": {
    "rating": 3.7,
    "slug": "the-blue-trail",
    "url": "https://letterboxd.com/film/the-blue-trail/"
  },
  "the cameraman": {
    "rating": 4.13,
    "slug": "the-cameraman",
    "url": "https://letterboxd.com/film/the-cameraman/"
  },
  "the canterbury tales": {
    "rating": 3.5,
    "slug": "the-canterbury-tales",
    "url": "https://letterboxd.com/film/the-canterbury-tales/"
  },
  "the cat returns": {
    "rating": 3.64,
    "slug": "the-cat-returns",
    "url": "https://letterboxd.com/film/the-cat-returns/"
  },
  "the celebration": {
    "rating": 4.32,
    "slug": "the-celebration",
    "url": "https://letterboxd.com/film/the-celebration/"
  },
  "the christophers": {},
  "the competition": {
    "rating": 3.52,
    "slug": "the-competition-2016",
    "url": "https://letterboxd.com/film/the-competition-2016/"
  },
  "the cook, the thief, his wife, and her lover": {},
  "the cry of jazz\n\n|  rewind & play": {},
  "the days": {
    "rating": null,
    "slug": "1994-dci-world-championships-legacy-collection",
    "url": "https://letterboxd.com/film/1994-dci-world-championships-legacy-collection/"
  },
  "the descent": {
    "rating": 3.57,
    "slug": "the-descent",
    "url": "https://letterboxd.com/film/the-descent/"
  },
  "the earrings of madame de\u2026": {
    "rating": 4.08,
    "slug": "the-earrings-of-madame-de",
    "url": "https://letterboxd.com/film/the-earrings-of-madame-de/"
  },
  "the english patient": {
    "rating": 3.62,
    "slug": "the-english-patient",
    "url": "https://letterboxd.com/film/the-english-patient/"
  },
  "the errand boy": {
    "rating": 3.56,
    "slug": "the-errand-boy",
    "url": "https://letterboxd.com/film/the-errand-boy/"
  },
  "the faculty": {},
  "the fall": {
    "rating": 4.24,
    "slug": "the-fall",
    "url": "https://letterboxd.com/film/the-fall/"
  },
  "the family jewels": {
    "rating": 3.4,
    "slug": "the-family-jewels",
    "url": "https://letterboxd.com/film/the-family-jewels/"
  },
  "the flavor of green tea over rice": {
    "rating": 4.03,
    "slug": "the-flavor-of-green-tea-over-rice",
    "url": "https://letterboxd.com/film/the-flavor-of-green-tea-over-rice/"
  },
  "the flow\n\n|  cosmonautop_remix\n\n|  the yukon river is frozen covering the memories of the summer fires\n\n|  the dream portal\n\n|  chanson pour kathy acker\n\n|  slower\n\n|  the beating eye\n\n|  i am present\n\n|  nasty nuns peacocking while the chickens watch xxx\n\n|  tiger lily mountain pass\n\n|  cold and dim\n\n|  anka\n\n|  pov: i am a vertigo that actively fails to define itself\n\n|  the thing that enjoys itself": {},
  "the flowers of st. francis": {},
  "the fly": {
    "rating": 4.0,
    "slug": "the-fly-1986",
    "url": "https://letterboxd.com/film/the-fly-1986/"
  },
  "the fox and the hound": {},
  "the french connection": {
    "rating": 3.99,
    "slug": "the-french-connection",
    "url": "https://letterboxd.com/film/the-french-connection/"
  },
  "the gambler": {
    "rating": 3.73,
    "slug": "the-gambler",
    "url": "https://letterboxd.com/film/the-gambler/"
  },
  "the girl in the snow": {
    "rating": 3.37,
    "slug": "the-girl-in-the-snow-2025",
    "url": "https://letterboxd.com/film/the-girl-in-the-snow-2025/"
  },
  "the girl with the hatbox": {
    "rating": 3.58,
    "slug": "the-girl-with-the-hat-box",
    "url": "https://letterboxd.com/film/the-girl-with-the-hat-box/"
  },
  "the gleaners and i": {
    "rating": 4.26,
    "slug": "the-gleaners-and-i",
    "url": "https://letterboxd.com/film/the-gleaners-and-i/"
  },
  "the gleaners and i: two years later": {
    "rating": 3.82,
    "slug": "the-gleaners-and-i-two-years-later",
    "url": "https://letterboxd.com/film/the-gleaners-and-i-two-years-later/"
  },
  "the good traitor": {
    "rating": 3.22,
    "slug": "the-good-traitor",
    "url": "https://letterboxd.com/film/the-good-traitor/"
  },
  "the good, the bad, the weird": {},
  "the gospel according to st. matthew": {},
  "the great arch": {
    "rating": 3.56,
    "slug": "the-great-arch-2025",
    "url": "https://letterboxd.com/film/the-great-arch-2025/"
  },
  "the greater circulation": {
    "rating": null,
    "slug": "the-greater-circulation",
    "url": "https://letterboxd.com/film/the-greater-circulation/"
  },
  "the hand": {},
  "the handmaiden": {},
  "the harder they come": {
    "rating": 3.7,
    "slug": "the-harder-they-come",
    "url": "https://letterboxd.com/film/the-harder-they-come/"
  },
  "the headless woman": {
    "rating": 3.62,
    "slug": "the-headless-woman",
    "url": "https://letterboxd.com/film/the-headless-woman/"
  },
  "the heroic trio": {
    "rating": 3.61,
    "slug": "the-heroic-trio",
    "url": "https://letterboxd.com/film/the-heroic-trio/"
  },
  "the holy girl": {
    "rating": 3.74,
    "slug": "the-holy-girl",
    "url": "https://letterboxd.com/film/the-holy-girl/"
  },
  "the holy mountain": {},
  "the house on trubnaya": {},
  "the informant!": {},
  "the invasion\n\n|  paleontology lesson": {},
  "the iron giant": {},
  "the island of loves": {
    "rating": 3.75,
    "slug": "island-of-loves",
    "url": "https://letterboxd.com/film/island-of-loves/"
  },
  "the killing of a sacred deer": {
    "rating": 3.7,
    "slug": "the-killing-of-a-sacred-deer",
    "url": "https://letterboxd.com/film/the-killing-of-a-sacred-deer/"
  },
  "the king of comedy": {
    "rating": 4.24,
    "slug": "the-king-of-comedy",
    "url": "https://letterboxd.com/film/the-king-of-comedy/"
  },
  "the kingdom\u2019s stone": {},
  "the ladies man": {
    "rating": 3.55,
    "slug": "the-ladies-man-1961",
    "url": "https://letterboxd.com/film/the-ladies-man-1961/"
  },
  "the lady and the duke": {},
  "the last emperor": {
    "rating": 3.94,
    "slug": "the-last-emperor",
    "url": "https://letterboxd.com/film/the-last-emperor/"
  },
  "the legend of suram fortress": {
    "rating": 3.88,
    "slug": "the-legend-of-suram-fortress",
    "url": "https://letterboxd.com/film/the-legend-of-suram-fortress/"
  },
  "the little sister": {
    "rating": 3.46,
    "slug": "the-little-sister-2025",
    "url": "https://letterboxd.com/film/the-little-sister-2025/"
  },
  "the love parade": {},
  "the love suicides at sonezaki": {
    "rating": 3.42,
    "slug": "double-suicide-of-sonezaki",
    "url": "https://letterboxd.com/film/double-suicide-of-sonezaki/"
  },
  "the love that remains": {
    "rating": 3.63,
    "slug": "the-love-that-remains",
    "url": "https://letterboxd.com/film/the-love-that-remains/"
  },
  "the loved one": {
    "rating": 3.44,
    "slug": "the-loved-one",
    "url": "https://letterboxd.com/film/the-loved-one/"
  },
  "the lovers on the bridge": {
    "rating": 4.24,
    "slug": "the-lovers-on-the-bridge",
    "url": "https://letterboxd.com/film/the-lovers-on-the-bridge/"
  },
  "the magician": {
    "rating": 3.81,
    "slug": "the-magician-1958",
    "url": "https://letterboxd.com/film/the-magician-1958/"
  },
  "the man from london": {
    "rating": 3.76,
    "slug": "the-man-from-london",
    "url": "https://letterboxd.com/film/the-man-from-london/"
  },
  "the man who shot liberty valance": {
    "rating": 4.29,
    "slug": "the-man-who-shot-liberty-valance",
    "url": "https://letterboxd.com/film/the-man-who-shot-liberty-valance/"
  },
  "the mansion of madness": {},
  "the masque of the red death": {
    "rating": 3.63,
    "slug": "the-masque-of-the-red-death",
    "url": "https://letterboxd.com/film/the-masque-of-the-red-death/"
  },
  "the matrix": {},
  "the milky way": {
    "rating": 3.66,
    "slug": "the-milky-way-1969",
    "url": "https://letterboxd.com/film/the-milky-way-1969/"
  },
  "the misfits": {
    "rating": 3.7,
    "slug": "the-misfits",
    "url": "https://letterboxd.com/film/the-misfits/"
  },
  "the money maker": {
    "rating": 3.41,
    "slug": "the-money-maker-2025",
    "url": "https://letterboxd.com/film/the-money-maker-2025/"
  },
  "the most terrible time in my life": {
    "rating": 3.81,
    "slug": "the-most-terrible-time-in-my-life",
    "url": "https://letterboxd.com/film/the-most-terrible-time-in-my-life/"
  },
  "the napa boys": {
    "rating": 3.39,
    "slug": "the-napa-boys",
    "url": "https://letterboxd.com/film/the-napa-boys/"
  },
  "the neverending story": {
    "rating": 3.62,
    "slug": "the-neverending-story",
    "url": "https://letterboxd.com/film/the-neverending-story/"
  },
  "the nutty professor": {
    "rating": 3.33,
    "slug": "the-nutty-professor",
    "url": "https://letterboxd.com/film/the-nutty-professor/"
  },
  "the old jockey": {
    "rating": null,
    "slug": "the-old-jockey",
    "url": "https://letterboxd.com/film/the-old-jockey/"
  },
  "the one": {},
  "the oracle": {
    "rating": null,
    "slug": "the-oracle-1993",
    "url": "https://letterboxd.com/film/the-oracle-1993/"
  },
  "the others": {
    "rating": 3.79,
    "slug": "the-others",
    "url": "https://letterboxd.com/film/the-others/"
  },
  "the outfit": {},
  "the outsider": {
    "rating": 3.38,
    "slug": "the-outsider-1981",
    "url": "https://letterboxd.com/film/the-outsider-1981/"
  },
  "the ozu diaries": {
    "rating": null,
    "slug": "the-ozu-diaries",
    "url": "https://letterboxd.com/film/the-ozu-diaries/"
  },
  "the passion according to g.h.": {},
  "the pawnbroker": {},
  "the perfect neighbor": {
    "rating": 3.69,
    "slug": "the-perfect-neighbour",
    "url": "https://letterboxd.com/film/the-perfect-neighbour/"
  },
  "the piano teacher": {
    "rating": 4.07,
    "slug": "the-piano-teacher",
    "url": "https://letterboxd.com/film/the-piano-teacher/"
  },
  "the place without limits": {
    "rating": 3.88,
    "slug": "the-place-without-limits",
    "url": "https://letterboxd.com/film/the-place-without-limits/"
  },
  "the player": {
    "rating": 4.01,
    "slug": "the-player",
    "url": "https://letterboxd.com/film/the-player/"
  },
  "the poem of the hayachine valley": {
    "rating": null,
    "slug": "the-poem-of-hayachine-valley",
    "url": "https://letterboxd.com/film/the-poem-of-hayachine-valley/"
  },
  "the potted psalm\n\n|  the petrified dog\n\n|  mr. frenhoffer and the minotaur\n\n|  the lead shoes": {},
  "the prince and the showgirl": {
    "rating": 3.16,
    "slug": "the-prince-and-the-showgirl",
    "url": "https://letterboxd.com/film/the-prince-and-the-showgirl/"
  },
  "the prince of nothingwood": {
    "rating": 3.47,
    "slug": "the-prince-of-nothingwood",
    "url": "https://letterboxd.com/film/the-prince-of-nothingwood/"
  },
  "the prophet": {},
  "the reckless moment": {
    "rating": 3.65,
    "slug": "the-reckless-moment",
    "url": "https://letterboxd.com/film/the-reckless-moment/"
  },
  "the red balloon\n\n|  white mane": {},
  "the red horse animation\n\n|  the b. beaver animation\n\n|  sister suzie cinema": {},
  "the red turtle": {},
  "the revolt of the toys\n\n|  inspiration\n\n|  romance\n\n|  dimensions of dialogue\n\n|  a ballad about green wood\n\n|  reci reci reci": {},
  "the revolution will not be televised": {
    "rating": 4.07,
    "slug": "the-revolution-will-not-be-televised",
    "url": "https://letterboxd.com/film/the-revolution-will-not-be-televised/"
  },
  "the rib of the greater bay area": {
    "rating": null,
    "slug": "the-rib-of-the-greater-bay-area",
    "url": "https://letterboxd.com/film/the-rib-of-the-greater-bay-area/"
  },
  "the river train": {},
  "the royal tenenbaums": {
    "rating": 4.11,
    "slug": "the-royal-tenenbaums",
    "url": "https://letterboxd.com/film/the-royal-tenenbaums/"
  },
  "the rules of the game": {
    "rating": 4.07,
    "slug": "the-rules-of-the-game",
    "url": "https://letterboxd.com/film/the-rules-of-the-game/"
  },
  "the runner": {
    "rating": 4.11,
    "slug": "the-runner",
    "url": "https://letterboxd.com/film/the-runner/"
  },
  "the salt fisherman\n\n|  upshot\n\n|  the present\n\n|  mare nostrum": {},
  "the same river twice": {
    "rating": null,
    "slug": "the-same-river-twice",
    "url": "https://letterboxd.com/film/the-same-river-twice/"
  },
  "the search": {
    "rating": null,
    "slug": "the-search-1980",
    "url": "https://letterboxd.com/film/the-search-1980/"
  },
  "the seasons": {
    "rating": 3.2,
    "slug": "the-seasons-2025",
    "url": "https://letterboxd.com/film/the-seasons-2025/"
  },
  "the second mother": {},
  "the secret agent": {
    "rating": 3.85,
    "slug": "the-secret-agent-2025",
    "url": "https://letterboxd.com/film/the-secret-agent-2025/"
  },
  "the secret life of pets": {},
  "the servant": {
    "rating": 4.14,
    "slug": "the-servant",
    "url": "https://letterboxd.com/film/the-servant/"
  },
  "the seven year itch": {
    "rating": 3.31,
    "slug": "the-seven-year-itch",
    "url": "https://letterboxd.com/film/the-seven-year-itch/"
  },
  "the seventh seal": {
    "rating": 4.33,
    "slug": "the-seventh-seal",
    "url": "https://letterboxd.com/film/the-seventh-seal/"
  },
  "the silence": {
    "rating": 4.01,
    "slug": "the-silence",
    "url": "https://letterboxd.com/film/the-silence/"
  },
  "the sixth sense": {
    "rating": 4.09,
    "slug": "the-sixth-sense",
    "url": "https://letterboxd.com/film/the-sixth-sense/"
  },
  "the snow woman": {
    "rating": 3.83,
    "slug": "the-snow-woman",
    "url": "https://letterboxd.com/film/the-snow-woman/"
  },
  "the sound of music": {},
  "the sound of summer": {},
  "the story of qiu ju": {
    "rating": null,
    "slug": "when-football-changed-forever-the-story-of-the-1991-1992-football-division-one-season",
    "url": "https://letterboxd.com/film/when-football-changed-forever-the-story-of-the-1991-1992-football-division-one-season/"
  },
  "the stranger": {
    "rating": 3.42,
    "slug": "the-stranger-2025-1",
    "url": "https://letterboxd.com/film/the-stranger-2025-1/"
  },
  "the streets of greenwood\n\n|  pregnant but equal: the fight for maternity benefits\n\n|  el pueblo se levanta": {},
  "the swimmer": {},
  "the taking of power by louis xiv": {
    "rating": 3.7,
    "slug": "the-taking-of-power-by-louis-xiv",
    "url": "https://letterboxd.com/film/the-taking-of-power-by-louis-xiv/"
  },
  "the tallest dwarf": {
    "rating": null,
    "slug": "the-tallest-dwarf",
    "url": "https://letterboxd.com/film/the-tallest-dwarf/"
  },
  "the thing from another world": {
    "rating": 3.38,
    "slug": "the-thing-from-another-world",
    "url": "https://letterboxd.com/film/the-thing-from-another-world/"
  },
  "the time that remains": {},
  "the trap": {
    "rating": 3.57,
    "slug": "the-trap-1996",
    "url": "https://letterboxd.com/film/the-trap-1996/"
  },
  "the travel companion": {},
  "the turin horse": {
    "rating": 4.23,
    "slug": "the-turin-horse",
    "url": "https://letterboxd.com/film/the-turin-horse/"
  },
  "the ugly stepsister": {
    "rating": 3.65,
    "slug": "the-ugly-stepsister",
    "url": "https://letterboxd.com/film/the-ugly-stepsister/"
  },
  "the unbearable lightness of being": {
    "rating": 3.67,
    "slug": "the-unbearable-lightness-of-being",
    "url": "https://letterboxd.com/film/the-unbearable-lightness-of-being/"
  },
  "the unsolved love hotel murder case incident": {},
  "the vanishing": {
    "rating": 4.01,
    "slug": "the-vanishing",
    "url": "https://letterboxd.com/film/the-vanishing/"
  },
  "the vanishing point": {
    "rating": null,
    "slug": "the-vanishing-point-2025",
    "url": "https://letterboxd.com/film/the-vanishing-point-2025/"
  },
  "the virgin's bed": {},
  "the voice of hind rajab": {
    "rating": 4.39,
    "slug": "the-voice-of-hind-rajab",
    "url": "https://letterboxd.com/film/the-voice-of-hind-rajab/"
  },
  "the warriors": {},
  "the watermelon woman": {
    "rating": 4.06,
    "slug": "the-watermelon-woman",
    "url": "https://letterboxd.com/film/the-watermelon-woman/"
  },
  "the whirled\n\n|  xcxhxexrxrxixexsx": {},
  "the whitest kids u\u2019know\u2019s mars": {},
  "the wicker man": {
    "rating": 3.97,
    "slug": "the-wicker-man",
    "url": "https://letterboxd.com/film/the-wicker-man/"
  },
  "the wind will carry us": {
    "rating": 4.08,
    "slug": "the-wind-will-carry-us",
    "url": "https://letterboxd.com/film/the-wind-will-carry-us/"
  },
  "the witch's mirror": {},
  "the wiz": {
    "rating": 3.45,
    "slug": "the-wiz",
    "url": "https://letterboxd.com/film/the-wiz/"
  },
  "the wizard of the kremlin": {
    "rating": 2.85,
    "slug": "the-wizard-of-the-kremlin",
    "url": "https://letterboxd.com/film/the-wizard-of-the-kremlin/"
  },
  "the works and days (of tayoko shiojiri in the shiotani basin)": {},
  "the world of jacques demy": {
    "rating": 3.77,
    "slug": "the-world-of-jacques-demy",
    "url": "https://letterboxd.com/film/the-world-of-jacques-demy/"
  },
  "the wreck of the new york subway\n\n|  elevator pitch\n\n|  end of the line": {},
  "the wrestler and the clown": {},
  "the young girls of rochefort": {
    "rating": 4.32,
    "slug": "the-young-girls-of-rochefort",
    "url": "https://letterboxd.com/film/the-young-girls-of-rochefort/"
  },
  "the young girls turn 25": {
    "rating": 3.8,
    "slug": "the-young-girls-turn-25",
    "url": "https://letterboxd.com/film/the-young-girls-turn-25/"
  },
  "thee whispering began\n\n|  psychic tv: dreams less sweet\n\n|  thee worm returns\n\n|  we kiss/starlit mire": {},
  "this closeness": {},
  "this one goes out to the dance\n\n|  palimpsest 1: now u see us\n\n|  the story of the cricket queen\n\n|  the house of doors\n\n|  spring rebirth at source du p\u00eacher\n\n|  the sleepwalker's song\n\n|  magic mountain\n\n|  eigengrau\n\n|  forever, in october\n\n|  my dog is dead and other griefffs\n\n|  apocalipsis\n\n|  snowy train": {},
  "thomas the impostor": {},
  "three ages": {
    "rating": 3.47,
    "slug": "three-ages",
    "url": "https://letterboxd.com/film/three-ages/"
  },
  "three colors: blue": {},
  "three colors: red": {},
  "three colors: white": {},
  "three crowns of the sailor": {
    "rating": 3.96,
    "slug": "three-crowns-of-the-sailor",
    "url": "https://letterboxd.com/film/three-crowns-of-the-sailor/"
  },
  "three on a couch": {
    "rating": 3.35,
    "slug": "three-on-a-couch",
    "url": "https://letterboxd.com/film/three-on-a-couch/"
  },
  "through the night": {
    "rating": 3.42,
    "slug": "through-the-night-2023",
    "url": "https://letterboxd.com/film/through-the-night-2023/"
  },
  "th\u00e9r\u00e8se desqueyroux": {
    "rating": 3.61,
    "slug": "therese-1962",
    "url": "https://letterboxd.com/film/therese-1962/"
  },
  "tiananmen": {},
  "time indefinite": {
    "rating": 3.97,
    "slug": "time-indefinite",
    "url": "https://letterboxd.com/film/time-indefinite/"
  },
  "titan a.e.": {},
  "to a land unknown": {
    "rating": 3.84,
    "slug": "to-a-land-unknown",
    "url": "https://letterboxd.com/film/to-a-land-unknown/"
  },
  "to hold a rabbit\n\n|  12 months first love\n\n|  a place to bury strangers\n\n|  a poem\n\n|  monad 5\n\n|  thunder": {},
  "to sleep with anger": {
    "rating": 3.92,
    "slug": "to-sleep-with-anger",
    "url": "https://letterboxd.com/film/to-sleep-with-anger/"
  },
  "to the left of the father": {
    "rating": 4.02,
    "slug": "to-the-left-of-the-father",
    "url": "https://letterboxd.com/film/to-the-left-of-the-father/"
  },
  "to the west, in zapata": {
    "rating": 3.57,
    "slug": "to-the-west-in-zapata",
    "url": "https://letterboxd.com/film/to-the-west-in-zapata/"
  },
  "todo parec\u00eda posible": {
    "rating": null,
    "slug": "everything-seemed-possible",
    "url": "https://letterboxd.com/film/everything-seemed-possible/"
  },
  "toledo, my father\n\n|  be mine sometime\n\n|  breath control\n\n|  mr. bound and gagged\n\n|  perchlorethylene [incomplete work-in-progress]": {},
  "tout va bien": {
    "rating": 3.64,
    "slug": "tout-va-bien",
    "url": "https://letterboxd.com/film/tout-va-bien/"
  },
  "train dreams": {
    "rating": 4.07,
    "slug": "train-dreams",
    "url": "https://letterboxd.com/film/train-dreams/"
  },
  "transit": {
    "rating": 3.88,
    "slug": "transit-2018",
    "url": "https://letterboxd.com/film/transit-2018/"
  },
  "travis": {},
  "trial of hein": {},
  "trip to bangkok, coffin included": {
    "rating": null,
    "slug": "trip-to-bangkok-coffin-included",
    "url": "https://letterboxd.com/film/trip-to-bangkok-coffin-included/"
  },
  "trouble every day": {
    "rating": 3.39,
    "slug": "trouble-every-day",
    "url": "https://letterboxd.com/film/trouble-every-day/"
  },
  "turk 182": {},
  "turkish paranormal activity": {},
  "twice into oblivion (l'oubli tue deux fois)\n\n|  los conjurados": {},
  "two mountains weighing down my chest": {},
  "two pianos": {
    "rating": 2.61,
    "slug": "two-pianos",
    "url": "https://letterboxd.com/film/two-pianos/"
  },
  "two prosecutors": {
    "rating": 3.41,
    "slug": "two-prosecutors",
    "url": "https://letterboxd.com/film/two-prosecutors/"
  },
  "two seasons, two strangers": {},
  "two wrenching departures": {},
  "tycoon": {
    "rating": null,
    "slug": "tycoon-2026",
    "url": "https://letterboxd.com/film/tycoon-2026/"
  },
  "under a shipwrecked moon": {
    "rating": null,
    "slug": "under-a-shipwrecked-moon",
    "url": "https://letterboxd.com/film/under-a-shipwrecked-moon/"
  },
  "under the tit\n\n|  a mixtape for stom": {},
  "undercover\n\n|  second notes\n\n|  montreal\n\n|  resistance meditation\n\n|  xtended release\n\n|  refrigerator hum\n\n|  ashes to ashes\n\n|  shed\n\n|  marratein, marratein": {},
  "undine": {
    "rating": 3.64,
    "slug": "undine-2020",
    "url": "https://letterboxd.com/film/undine-2020/"
  },
  "unraveling george\n\n|  open book: the scandal that shook up college basketball": {},
  "urusei yatsura 2: beautiful dreamer": {
    "rating": 3.95,
    "slug": "urusei-yatsura-beautiful-dreamer",
    "url": "https://letterboxd.com/film/urusei-yatsura-beautiful-dreamer/"
  },
  "va savoir": {
    "rating": 3.81,
    "slug": "va-savoir-who-knows",
    "url": "https://letterboxd.com/film/va-savoir-who-knows/"
  },
  "vagabond": {
    "rating": 4.1,
    "slug": "vagabond",
    "url": "https://letterboxd.com/film/vagabond/"
  },
  "vampire time travelers": {
    "rating": 3.26,
    "slug": "vampire-time-travelers",
    "url": "https://letterboxd.com/film/vampire-time-travelers/"
  },
  "vampires of the velvet lounge": {
    "rating": null,
    "slug": "vampires-of-the-velvet-lounge",
    "url": "https://letterboxd.com/film/vampires-of-the-velvet-lounge/"
  },
  "varda by agn\u00e8s": {
    "rating": 4.07,
    "slug": "varda-by-agnes",
    "url": "https://letterboxd.com/film/varda-by-agnes/"
  },
  "variations on a theme": {},
  "variety": {
    "rating": 3.48,
    "slug": "variety",
    "url": "https://letterboxd.com/film/variety/"
  },
  "veronika voss": {},
  "video bunt (at the new wal-mart across the street from the old wal-mart)\n\n|  rip van winkle\n\n|  springtime\n\n|  auto-autumnals\n\n|  nature mature\n\n|  history minor\n\n|  occupations\n\n|  we never sleep": {},
  "vintage: families of value\n\n|  an untitled portrait": {},
  "waiting for guffman": {
    "rating": 3.84,
    "slug": "waiting-for-guffman",
    "url": "https://letterboxd.com/film/waiting-for-guffman/"
  },
  "wajib": {
    "rating": 3.92,
    "slug": "wajib",
    "url": "https://letterboxd.com/film/wajib/"
  },
  "waking life": {},
  "wandering ginza butterfly": {},
  "warm decembers\n\n|  a map of the pit\n\n|  hymnal (selected excerpts)": {},
  "wavelength": {
    "rating": 3.52,
    "slug": "wavelength-1967",
    "url": "https://letterboxd.com/film/wavelength-1967/"
  },
  "we won't grow old together": {
    "rating": 3.87,
    "slug": "we-wont-grow-old-together",
    "url": "https://letterboxd.com/film/we-wont-grow-old-together/"
  },
  "weekend": {
    "rating": 3.74,
    "slug": "weekend-1967",
    "url": "https://letterboxd.com/film/weekend-1967/"
  },
  "welfare": {
    "rating": 4.32,
    "slug": "welfare",
    "url": "https://letterboxd.com/film/welfare/"
  },
  "werckmeister harmonies": {
    "rating": 4.31,
    "slug": "werckmeister-harmonies",
    "url": "https://letterboxd.com/film/werckmeister-harmonies/"
  },
  "werewolf": {
    "rating": 3.03,
    "slug": "frankensteins-bloody-terror",
    "url": "https://letterboxd.com/film/frankensteins-bloody-terror/"
  },
  "west indies: the fugitive slaves of liberty": {
    "rating": 4.08,
    "slug": "west-indies",
    "url": "https://letterboxd.com/film/west-indies/"
  },
  "what does that nature say to you": {
    "rating": 3.7,
    "slug": "what-does-that-nature-say-to-you",
    "url": "https://letterboxd.com/film/what-does-that-nature-say-to-you/"
  },
  "what time is it there?": {},
  "what's opera, doc?\n\n|  sculpture for children\n\n|  the existentialist\n\n|  waterfall\n\n|  manhatta\n\n|  something queer at the library": {},
  "where is the friend's house?": {
    "rating": 4.38,
    "slug": "where-is-the-friends-house",
    "url": "https://letterboxd.com/film/where-is-the-friends-house/"
  },
  "whistle stop": {},
  "who moves america": {},
  "who's afraid of virginia woolf?": {
    "rating": 4.27,
    "slug": "whos-afraid-of-virginia-woolf",
    "url": "https://letterboxd.com/film/whos-afraid-of-virginia-woolf/"
  },
  "why has bodhi-dharma left for the east?": {
    "rating": 3.93,
    "slug": "why-has-bodhi-dharma-left-for-the-east",
    "url": "https://letterboxd.com/film/why-has-bodhi-dharma-left-for-the-east/"
  },
  "wishbone": {
    "rating": null,
    "slug": "wishbone-2024",
    "url": "https://letterboxd.com/film/wishbone-2024/"
  },
  "would you like to meet your neighbor? a new york subway tape\n\n|  dark days": {},
  "wreck-it ralph": {},
  "written on the wind": {
    "rating": 3.88,
    "slug": "written-on-the-wind",
    "url": "https://letterboxd.com/film/written-on-the-wind/"
  },
  "www.rachelormont.com": {},
  "yakuza graveyard": {
    "rating": 3.67,
    "slug": "yakuza-graveyard",
    "url": "https://letterboxd.com/film/yakuza-graveyard/"
  },
  "you're next": {
    "rating": 3.34,
    "slug": "youre-next",
    "url": "https://letterboxd.com/film/youre-next/"
  },
  "young soul rebels": {},
  "zodiac": {
    "rating": 4.02,
    "slug": "zodiac",
    "url": "https://letterboxd.com/film/zodiac/"
  },
  "\u00e8 piccerella": {}
}